<annotation><size><width>1080</width><height>1920</height><depth>3</depth></size><segmented>0</segmented><object><name>SMA</name><bndbox><xmin>740</xmin><ymin>623</ymin><xmax>858</xmax><ymax>738</ymax></bndbox></object><object><name>SMA</name><bndbox><xmin>893</xmin><ymin>710</ymin><xmax>1014</xmax><ymax>830</ymax></bndbox></object><object><name>SMA</name><bndbox><xmin>945</xmin><ymin>827</ymin><xmax>1076</xmax><ymax>955</ymax></bndbox></object><object><name>SMA</name><bndbox><xmin>786</xmin><ymin>742</ymin><xmax>909</xmax><ymax>867</ymax></bndbox></object><object><name>SMA</name><bndbox><xmin>683</xmin><ymin>782</ymin><xmax>803</xmax><ymax>900</ymax></bndbox></object><object><name>SMA</name><bndbox><xmin>837</xmin><ymin>873</ymin><xmax>963</xmax><ymax>994</ymax></bndbox></object><object><name>SMA</name><bndbox><xmin>740</xmin><ymin>909</ymin><xmax>866</xmax><ymax>1033</ymax></bndbox></object></annotation>