<annotation><size><width>1080</width><height>1920</height><depth>3</depth></size><segmented>0</segmented><object><name>SMA</name><bndbox><xmin>169</xmin><ymin>561</ymin><xmax>376</xmax><ymax>758</ymax></bndbox></object><object><name>SMA</name><bndbox><xmin>432</xmin><ymin>514</ymin><xmax>648</xmax><ymax>732</ymax></bndbox></object><object><name>SMA</name><bndbox><xmin>754</xmin><ymin>734</ymin><xmax>968</xmax><ymax>952</ymax></bndbox></object><object><name>SMA</name><bndbox><xmin>433</xmin><ymin>764</ymin><xmax>648</xmax><ymax>972</ymax></bndbox></object><object><name>SMA</name><bndbox><xmin>163</xmin><ymin>808</ymin><xmax>367</xmax><ymax>991</ymax></bndbox></object><object><name>SMA</name><bndbox><xmin>131</xmin><ymin>1028</ymin><xmax>360</xmax><ymax>1222</ymax></bndbox></object><object><name>SMA</name><bndbox><xmin>416</xmin><ymin>1022</ymin><xmax>659</xmax><ymax>1249</ymax></bndbox></object></annotation>