<annotation><size><width>1080</width><height>1920</height><depth>3</depth></size><segmented>0</segmented><object><name>SMA</name><bndbox><xmin>173</xmin><ymin>497</ymin><xmax>400</xmax><ymax>721</ymax></bndbox></object><object><name>SMA</name><bndbox><xmin>157</xmin><ymin>840</ymin><xmax>396</xmax><ymax>1074</ymax></bndbox></object><object><name>SMA</name><bndbox><xmin>349</xmin><ymin>717</ymin><xmax>577</xmax><ymax>942</ymax></bndbox></object><object><name>SMA</name><bndbox><xmin>534</xmin><ymin>575</ymin><xmax>767</xmax><ymax>805</ymax></bndbox></object><object><name>SMA</name><bndbox><xmin>333</xmin><ymin>1070</ymin><xmax>594</xmax><ymax>1330</ymax></bndbox></object><object><name>SMA</name><bndbox><xmin>543</xmin><ymin>925</ymin><xmax>785</xmax><ymax>1167</ymax></bndbox></object><object><name>SMA</name><bndbox><xmin>714</xmin><ymin>795</ymin><xmax>971</xmax><ymax>1043</ymax></bndbox></object></annotation>