<annotation><size><width>1080</width><height>1920</height><depth>3</depth></size><segmented>0</segmented><object><name>SMA</name><bndbox><xmin>553</xmin><ymin>788</ymin><xmax>737</xmax><ymax>988</ymax></bndbox></object><object><name>SMA</name><bndbox><xmin>197</xmin><ymin>654</ymin><xmax>377</xmax><ymax>866</ymax></bndbox></object><object><name>SMA</name><bndbox><xmin>261</xmin><ymin>878</ymin><xmax>435</xmax><ymax>1084</ymax></bndbox></object><object><name>SMA</name><bndbox><xmin>333</xmin><ymin>1144</ymin><xmax>515</xmax><ymax>1324</ymax></bndbox></object><object><name>SMA</name><bndbox><xmin>9</xmin><ymin>1212</ymin><xmax>215</xmax><ymax>1418</ymax></bndbox></object><object><name>SMA</name><bndbox><xmin>1</xmin><ymin>992</ymin><xmax>159</xmax><ymax>1176</ymax></bndbox></object></annotation>